TwitterGraph/__init__.py
TwitterGraph/datascrapper.py
TwitterGraph/main.py
TwitterGraph/manager.py
TwitterGraph/multigraph.py
TwitterGraph/tree.py
tw_osint-0.0.9.dist-info/METADATA
tw_osint-0.0.9.dist-info/WHEEL
tw_osint-0.0.9.dist-info/entry_points.txt
tw_osint-0.0.9.dist-info/top_level.txt
tw_osint-0.0.9.dist-info/RECORD
